reachy2_sdk_api/__init__.py
reachy2_sdk_api/arm_pb2.py
reachy2_sdk_api/arm_pb2_grpc.py
reachy2_sdk_api/audio_pb2.py
reachy2_sdk_api/audio_pb2_grpc.py
reachy2_sdk_api/component_pb2.py
reachy2_sdk_api/component_pb2_grpc.py
reachy2_sdk_api/dynamixel_motor_pb2.py
reachy2_sdk_api/dynamixel_motor_pb2_grpc.py
reachy2_sdk_api/error_pb2.py
reachy2_sdk_api/error_pb2_grpc.py
reachy2_sdk_api/goto_pb2.py
reachy2_sdk_api/goto_pb2_grpc.py
reachy2_sdk_api/hand_pb2.py
reachy2_sdk_api/hand_pb2_grpc.py
reachy2_sdk_api/head_pb2.py
reachy2_sdk_api/head_pb2_grpc.py
reachy2_sdk_api/kinematics_pb2.py
reachy2_sdk_api/kinematics_pb2_grpc.py
reachy2_sdk_api/mobile_base_lidar_pb2.py
reachy2_sdk_api/mobile_base_lidar_pb2_grpc.py
reachy2_sdk_api/mobile_base_mobility_pb2.py
reachy2_sdk_api/mobile_base_mobility_pb2_grpc.py
reachy2_sdk_api/mobile_base_utility_pb2.py
reachy2_sdk_api/mobile_base_utility_pb2_grpc.py
reachy2_sdk_api/orbita2d_pb2.py
reachy2_sdk_api/orbita2d_pb2_grpc.py
reachy2_sdk_api/orbita3d_pb2.py
reachy2_sdk_api/orbita3d_pb2_grpc.py
reachy2_sdk_api/parallel_gripper_pb2.py
reachy2_sdk_api/parallel_gripper_pb2_grpc.py
reachy2_sdk_api/part_pb2.py
reachy2_sdk_api/part_pb2_grpc.py
reachy2_sdk_api/reachy_pb2.py
reachy2_sdk_api/reachy_pb2_grpc.py
reachy2_sdk_api/sound_pb2.py
reachy2_sdk_api/sound_pb2_grpc.py
reachy2_sdk_api/tripod_pb2.py
reachy2_sdk_api/tripod_pb2_grpc.py
reachy2_sdk_api/video_pb2.py
reachy2_sdk_api/video_pb2_grpc.py
reachy2_sdk_api/webrtc_bridge_pb2.py
reachy2_sdk_api/webrtc_bridge_pb2_grpc.py
reachy2_sdk_api-1.0.20.dist-info/METADATA
reachy2_sdk_api-1.0.20.dist-info/WHEEL
reachy2_sdk_api-1.0.20.dist-info/top_level.txt
reachy2_sdk_api-1.0.20.dist-info/RECORD
