Metadata-Version: 2.1
Name: reachy2-sdk-api
Version: 1.0.20
Summary: gRPC Protobuf API definition for Reachy 2 SDK
Home-page: https://github.com/pollen-robotics/reachy2-sdk-api
Author: Pollen Robotics
Author-email: contact@pollen-robotics.com
Requires-Dist: grpcio<=1.73.1,>=1.59.0
Requires-Dist: grpcio-tools<=1.73.1,>=1.59.0
Requires-Dist: protobuf<=6.32.0,>=4.25.0
